LICENSE
MANIFEST.in
README.rst
setup.cfg
setup.py
dredd_hooks/__init__.py
dredd_hooks/__main__.py
dredd_hooks/cli.py
dredd_hooks/dredd.py
dredd_hooks.egg-info/PKG-INFO
dredd_hooks.egg-info/SOURCES.txt
dredd_hooks.egg-info/dependency_links.txt
dredd_hooks.egg-info/entry_points.txt
dredd_hooks.egg-info/top_level.txt
dredd_hooks.egg-info/zip-safe
test/__init__.py
test/test_dredd_hooks.py
test/test_excepts_hook.py
test/test_multi_hooks.py