Metadata-Version: 1.2
Name: dredd-hooks
Version: 0.2.0
Summary: Python Hooks Bridge for Dredd API Testing Framework
Home-page: https://github.com/apiaryio/dredd-hooks-python/
Author: Vilibald Wanča
Author-email: vilibald.wanca@oracle.com
Maintainer: Apiary
Maintainer-email: support@apiary.io
License: MIT License
Download-URL: http://pypi.python.org/pypi/dredd_hooks
Keywords: HTTP API testing Dredd
Platform: any
Classifier: Development Status :: 5 - Production/Stable
Classifier: Environment :: Console
Classifier: Environment :: Web Environment
Classifier: Intended Audience :: Developers
Classifier: License :: OSI Approved :: MIT License
Classifier: Operating System :: OS Independent
Classifier: Programming Language :: Python :: 2
Classifier: Programming Language :: Python :: 3
Classifier: Topic :: Software Development :: Testing
Classifier: Topic :: Software Development :: Build Tools
